pganonymizer/__init__.py
pganonymizer/anonymize.py
pganonymizer/dsn.py
pganonymizer/helper.py
pganonymizer/tests/__init__.py
pganonymizer/tests/test_anonymize.py
pganonymizer-0.0.5.dist-info/LICENSE
pganonymizer-0.0.5.dist-info/METADATA
pganonymizer-0.0.5.dist-info/WHEEL
pganonymizer-0.0.5.dist-info/entry_points.txt
pganonymizer-0.0.5.dist-info/top_level.txt
pganonymizer-0.0.5.dist-info/RECORD
