Metadata-Version: 2.1
Name: pganonymizer
Version: 0.0.5
Summary: Database anonymizer package
Home-page: https://github.com/pypa/sampleproject
Author: Pattarawut Imamnuaysup
Author-email: pattarawut@hot-now.com
License: UNKNOWN
Platform: UNKNOWN
Classifier: Programming Language :: Python :: 3
Classifier: License :: OSI Approved :: MIT License
Classifier: Operating System :: OS Independent
Requires-Python: >=3.5
Requires-Dist: asyncpg
Requires-Dist: csj-parser
Requires-Dist: click
Requires-Dist: asyncio
Requires-Dist: pytest-asyncio
